singlue/__init__.py
singlue/main.py
singlue-0.1.5.dist-info/entry_points.txt
singlue-0.1.5.dist-info/WHEEL
singlue-0.1.5.dist-info/METADATA
singlue-0.1.5.dist-info/RECORD
