Metadata-Version: 2.1
Name: singlue
Version: 0.1.5
Summary: 
Author: kawagh
Author-email: kawagh@example.com
Requires-Python: >=3.9,<4.0
Classifier: Programming Language :: Python :: 3
Classifier: Programming Language :: Python :: 3.10
Classifier: Programming Language :: Python :: 3.9
